uw_coda/VERSION
uw_coda/__init__.py
uw_coda/dao.py
uw_coda/test.py
uw_coda/resources/coda/file/api/v1/course/2014-winter-POL S-201-A/cgpa
uw_coda/resources/coda/file/api/v1/course/2014-winter-POL S-201-A/fail_rate
uw_coda/resources/coda/file/api/v1/course/2014-winter-POL S-201-A/majors/2
uw_coda/tests/__init__.py
uw_coda/tests/test_endpoints.py
uw_restclients_coda-1.0.4.dist-info/licenses/LICENSE
uw_restclients_coda-1.0.4.dist-info/METADATA
uw_restclients_coda-1.0.4.dist-info/WHEEL
uw_restclients_coda-1.0.4.dist-info/top_level.txt
uw_restclients_coda-1.0.4.dist-info/RECORD
